<?xml version="1.0" encoding="UTF-8"?>
<MetaDataObject xmlns="http://v8.1c.ru/8.3/MDClasses" xmlns:app="http://v8.1c.ru/8.2/managed-application/core" xmlns:cfg="http://v8.1c.ru/8.1/data/enterprise/current-config" xmlns:cmi="http://v8.1c.ru/8.2/managed-application/cmi" xmlns:ent="http://v8.1c.ru/8.1/data/enterprise" xmlns:lf="http://v8.1c.ru/8.2/managed-application/logform" xmlns:style="http://v8.1c.ru/8.1/data/ui/style" xmlns:sys="http://v8.1c.ru/8.1/data/ui/fonts/system" xmlns:v8="http://v8.1c.ru/8.1/data/core" xmlns:v8ui="http://v8.1c.ru/8.1/data/ui" xmlns:web="http://v8.1c.ru/8.1/data/ui/colors/web" xmlns:win="http://v8.1c.ru/8.1/data/ui/colors/windows" xmlns:xen="http://v8.1c.ru/8.3/xcf/enums" xmlns:xpr="http://v8.1c.ru/8.3/xcf/predef" xmlns:xr="http://v8.1c.ru/8.3/xcf/readable" xmlns:xs="http://www.w3.org/2001/XMLSchema" xmlns:xsi="http://www.w3.org/2001/XMLSchema-instance" version="2.10">
	<Constant uuid="ab04cdcb-dc48-4252-9bb5-efc0097f0d24">
		<InternalInfo>
			<xr:GeneratedType name="ConstantManager.ИспользоватьБизнесРегионы" category="Manager">
				<xr:TypeId>ddbb97e2-659c-4212-bf75-d7e172b0dff0</xr:TypeId>
				<xr:ValueId>bd30bbae-9faf-4329-ab13-3da54efe625b</xr:ValueId>
			</xr:GeneratedType>
			<xr:GeneratedType name="ConstantValueManager.ИспользоватьБизнесРегионы" category="ValueManager">
				<xr:TypeId>33afaccc-f01d-43d9-8bb9-6b43a63d3f64</xr:TypeId>
				<xr:ValueId>3c8da046-3f67-4f91-9539-21bbde61632c</xr:ValueId>
			</xr:GeneratedType>
			<xr:GeneratedType name="ConstantValueKey.ИспользоватьБизнесРегионы" category="ValueKey">
				<xr:TypeId>fa2d36b8-c177-5700-ac4e-b36f08b1d650</xr:TypeId>
				<xr:ValueId>c516ab5d-7fcf-5e7b-80c7-26fd204a5549</xr:ValueId>
			</xr:GeneratedType>
		</InternalInfo>
		<Properties>
			<Name>ИспользоватьБизнесРегионы</Name>
			<Comment/>
			<ObjectBelonging>Adopted</ObjectBelonging>
			<Type>
				<v8:Type>xs:boolean</v8:Type>
			</Type>
		</Properties>
	</Constant>
</MetaDataObject>